AgenciBr/Alexandre.py
AgenciBr/Ana.py
AgenciBr/Ideam.py
AgenciBr/Inemet.py
AgenciBr/Merge.py
AgenciBr/__init__.py
AgenciBr/indice.py
AgenciBr-0.1.7.dist-info/LICENSE
AgenciBr-0.1.7.dist-info/METADATA
AgenciBr-0.1.7.dist-info/WHEEL
AgenciBr-0.1.7.dist-info/top_level.txt
AgenciBr-0.1.7.dist-info/RECORD
