Metadata-Version: 2.1
Name: AgenciBr
Version: 0.1.7
Summary: Package to work with data from brazilian agenci
Home-page: UNKNOWN
Author: Thiago Santos
Author-email: tthiagosantos38@gmail.com
License: MIT License
Keywords: Ana,Inemet,Ideam
Platform: UNKNOWN
License-File: LICENSE
Requires-Dist: cfgrib
Requires-Dist: datetime
Requires-Dist: geopandas
Requires-Dist: matplotlib
Requires-Dist: netCDF4
Requires-Dist: numpy
Requires-Dist: pandas
Requires-Dist: requests
Requires-Dist: xarray
